Haxanime/__init__.py
Haxanime/getanime.py
Haxanime-1.0.0.dist-info/LICENSE.txt
Haxanime-1.0.0.dist-info/METADATA
Haxanime-1.0.0.dist-info/WHEEL
Haxanime-1.0.0.dist-info/top_level.txt
Haxanime-1.0.0.dist-info/RECORD
