Metadata-Version: 2.1
Name: Haxanime
Version: 1.0.0
Summary: A Python package to download anime from command line
Home-page: https://github.com/devoply-dev/cmdweeebs
Author: Elenasulu Arinze
Author-email: pentacker@gmail.com
License: "MIT"
Project-URL: repository, https://github.com/devoply-dev/cmdweeebs
Keywords: ["pypi","getanime","Haxanime","anime downloader"]
Classifier: Environment :: Console
Classifier: Natural Language :: English
Classifier: Topic :: Home Automation
Classifier: Development Status :: 5 - Production/Stable
Classifier: Programming Language :: Python :: 3
Classifier: License :: OSI Approved :: MIT License
Classifier: Operating System :: OS Independent
Requires-Python: >=3.7
License-File: LICENSE.txt
